nupunkt/__init__.py
nupunkt/_version.py
nupunkt/cli.py
nupunkt/cli_model_utils.py
nupunkt/py.typed
nupunkt/core/__init__.py
nupunkt/core/base.py
nupunkt/core/constants.py
nupunkt/core/language_vars.py
nupunkt/core/parameters.py
nupunkt/core/tokens.py
nupunkt/evaluation/__init__.py
nupunkt/evaluation/dataset.py
nupunkt/evaluation/evaluator.py
nupunkt/evaluation/metrics.py
nupunkt/hybrid/__init__.py
nupunkt/hybrid/adaptive_tokenizer.py
nupunkt/hybrid/confidence_tokenizer.py
nupunkt/hybrid/confidence_tokenizer_fixed.py
nupunkt/models/__init__.py
nupunkt/models/default_model.json.gz
nupunkt/optimization/__init__.py
nupunkt/optimization/discovery.py
nupunkt/optimization/hyperparameter.py
nupunkt/tokenizers/__init__.py
nupunkt/tokenizers/paragraph_tokenizer.py
nupunkt/tokenizers/sentence_tokenizer.py
nupunkt/trainers/__init__.py
nupunkt/trainers/base_trainer.py
nupunkt/training/__init__.py
nupunkt/training/core.py
nupunkt/training/hyperparameters.py
nupunkt/training/optimizer.py
nupunkt/utils/__init__.py
nupunkt/utils/compression.py
nupunkt/utils/iteration.py
nupunkt/utils/paths.py
nupunkt/utils/statistics.py
nupunkt/workflows/__init__.py
nupunkt/workflows/automated_training.py
nupunkt-0.6.0.dist-info/licenses/LICENSE
nupunkt-0.6.0.dist-info/METADATA
nupunkt-0.6.0.dist-info/WHEEL
nupunkt-0.6.0.dist-info/entry_points.txt
nupunkt-0.6.0.dist-info/top_level.txt
nupunkt-0.6.0.dist-info/RECORD
