Metadata-Version: 2.4
Name: nupunkt
Version: 0.6.0
Summary: Next-generation Punkt sentence and paragraph boundary detection with zero dependencies
Author-email: ALEA Institute <hello@aleainstitute.ai>
License-Expression: MIT
Project-URL: Homepage, https://github.com/alea-institute/nupunkt
Project-URL: Source, https://github.com/alea-institute/nupunkt
Project-URL: Bug Tracker, https://github.com/alea-institute/nupunkt/issues
Project-URL: Changelog, https://github.com/alea-institute/nupunkt/blob/main/CHANGELOG.md
Keywords: nlp,natural language processing,tokenization,sentence boundary detection,paragraph detection,punkt,text processing,linguistics
Classifier: Development Status :: 4 - Beta
Classifier: Intended Audience :: Developers
Classifier: Intended Audience :: Science/Research
Classifier: Programming Language :: Python :: 3
Classifier: Programming Language :: Python :: 3.11
Classifier: Programming Language :: Python :: 3.12
Classifier: Programming Language :: Python :: 3.13
Classifier: Programming Language :: Python :: 3.14
Classifier: Topic :: Scientific/Engineering :: Artificial Intelligence
Classifier: Topic :: Text Processing :: Linguistic
Classifier: Natural Language :: English
Classifier: Operating System :: OS Independent
Requires-Python: >=3.11
License-File: LICENSE
Provides-Extra: dev
Requires-Dist: tqdm==4.66.1; extra == "dev"
Requires-Dist: pytest==8.3.2; extra == "dev"
Requires-Dist: mypy==1.11.2; extra == "dev"
Requires-Dist: ruff==0.6.5; extra == "dev"
Requires-Dist: black==24.8.0; extra == "dev"
Requires-Dist: pytest-benchmark==5.1.0; extra == "dev"
Requires-Dist: pytest-cov==6.0.0; extra == "dev"
Requires-Dist: memory-profiler>=0.61.0; extra == "dev"
Requires-Dist: psutil>=7.0.0; extra == "dev"
Provides-Extra: docs
Requires-Dist: sphinx==7.3.7; extra == "docs"
Requires-Dist: sphinx-rtd-theme==2.0.0; extra == "docs"
Requires-Dist: myst-parser==4.0.0; extra == "docs"
Provides-Extra: training
Requires-Dist: tokenizers>=0.21.0; extra == "training"
Requires-Dist: datasets>=2.19.0; extra == "training"
Dynamic: license-file
